sparkplug_avatars/__init__.py
sparkplug_avatars/apps.py
sparkplug_avatars/factories.py
sparkplug_avatars/migrations/0001_initial.py
sparkplug_avatars/migrations/0002_auto_20210607_2228.py
sparkplug_avatars/migrations/0003_alter_avatar_created_alter_avatar_modified.py
sparkplug_avatars/migrations/__init__.py
sparkplug_avatars/models/__init__.py
sparkplug_avatars/models/avatar.py
sparkplug_avatars/serializers/__init__.py
sparkplug_avatars/serializers/detail.py
sparkplug_avatars/serializers/upload.py
sparkplug_avatars/services/__init__.py
sparkplug_avatars/services/get_thumbnail_url.py
sparkplug_avatars/services/image_optimizer.py
sparkplug_avatars/services/process_avatar.py
sparkplug_avatars/signals.py
sparkplug_avatars/tasks/__init__.py
sparkplug_avatars/tasks/process_avatar.py
sparkplug_avatars/tests/__init__.py
sparkplug_avatars/tests/serializers/__init__.py
sparkplug_avatars/tests/serializers/test_detail.py
sparkplug_avatars/tests/serializers/test_upload.py
sparkplug_avatars/tests/services/__init__.py
sparkplug_avatars/tests/services/test_get_thumbnail_url.py
sparkplug_avatars/tests/services/test_image_optimizer.py
sparkplug_avatars/tests/services/test_process_avatar.py
sparkplug_avatars/tests/utils/__init__.py
sparkplug_avatars/tests/utils/test_get_upload_location.py
sparkplug_avatars/tests/views/__init__.py
sparkplug_avatars/tests/views/test_upload.py
sparkplug_avatars/urls.py
sparkplug_avatars/utils/__init__.py
sparkplug_avatars/utils/get_upload_location.py
sparkplug_avatars/views/__init__.py
sparkplug_avatars/views/upload.py
sparkplug_api_avatars-1.1.4.dist-info/METADATA
sparkplug_api_avatars-1.1.4.dist-info/WHEEL
sparkplug_api_avatars-1.1.4.dist-info/RECORD
