Metadata-Version: 2.3
Name: sparkplug-api-avatars
Version: 1.1.4
Summary: Avatar package for Sparkplug apps
License: MIT
Author: Sparkplug Marcus
Author-email: sparkplugmarcus@gmail.com
Requires-Python: >=3.11,<4.0
Classifier: License :: OSI Approved :: MIT License
Classifier: Programming Language :: Python :: 3
Classifier: Programming Language :: Python :: 3.11
Classifier: Programming Language :: Python :: 3.12
Classifier: Programming Language :: Python :: 3.13
Requires-Dist: Pillow (>=11.3.0,<11.4.0)
Requires-Dist: sorl-thumbnail (>=12.11.0,<12.12.0)
Requires-Dist: sparkplug-api-core (>=1.1.5,<1.2.0)
